{
  "sheetsById": {
    "Scene": {
      "staticOverrides": {
        "byObject": {}
      },
      "sequence": {
        "subUnitsPerUnit": 30,
        "length": 10,
        "type": "PositionalSequence",
        "tracksByObject": {
          "Armor": {
            "trackData": {
              "JVi37YVWqn": {
                "type": "BasicKeyframedTrack",
                "__debugName": "Armor:[\"position\",\"x\"]",
                "keyframes": [
                  {
                    "id": "wYXTjuvvN4",
                    "position": 0,
                    "connectedRight": true,
                    "handles": [
                      0.5,
                      1,
                      0.5,
                      0
                    ],
                    "type": "bezier",
                    "value": 1.6
                  },
                  {
                    "id": "wEuxU47VJH",
                    "position": 1.067,
                    "connectedRight": true,
                    "handles": [
                      0.5,
                      1,
                      0.5,
                      0
                    ],
                    "type": "bezier",
                    "value": 1.6
                  },
                  {
                    "id": "TpiAdOfZuw",
                    "position": 1.8,
                    "connectedRight": true,
                    "handles": [
                      0.5,
                      1,
                      0.5,
                      0
                    ],
                    "type": "bezier",
                    "value": 1.6
                  },
                  {
                    "id": "GE7UUer80Q",
                    "position": 2.367,
                    "connectedRight": true,
                    "handles": [
                      0.5,
                      1,
                      0.5,
                      0
                    ],
                    "type": "bezier",
                    "value": 1.6
                  },
                  {
                    "id": "Vq2DFKRSIX",
                    "position": 2.967,
                    "connectedRight": true,
                    "handles": [
                      0.5,
                      1,
                      0.5,
                      0
                    ],
                    "type": "bezier",
                    "value": 1.6
                  },
                  {
                    "id": "lDQhbvYj6O",
                    "position": 3.533,
                    "connectedRight": true,
                    "handles": [
                      0.5,
                      1,
                      0.5,
                      0
                    ],
                    "type": "bezier",
                    "value": 1.6
                  },
                  {
                    "id": "surBcUpRk7",
                    "position": 4.133,
                    "connectedRight": true,
                    "handles": [
                      0.5,
                      1,
                      0.5,
                      0
                    ],
                    "type": "bezier",
                    "value": 1.8
                  },
                  {
                    "id": "PzA2GrT6jY",
                    "position": 4.733,
                    "connectedRight": true,
                    "handles": [
                      0.5,
                      1,
                      0.5,
                      0
                    ],
                    "type": "bezier",
                    "value": 1.8
                  },
                  {
                    "id": "grEY0BlNcO",
                    "position": 5.367,
                    "connectedRight": true,
                    "handles": [
                      0.5,
                      1,
                      0.5,
                      0
                    ],
                    "type": "bezier",
                    "value": 1.8
                  },
                  {
                    "id": "CdrZ8kcoNx",
                    "position": 5.9,
                    "connectedRight": true,
                    "handles": [
                      0.5,
                      1,
                      0.5,
                      0
                    ],
                    "type": "bezier",
                    "value": 1.8
                  },
                  {
                    "id": "DHoaaz3_ij",
                    "position": 7.667,
                    "connectedRight": true,
                    "handles": [
                      0.5,
                      1,
                      0.5,
                      0
                    ],
                    "type": "bezier",
                    "value": 1.8
                  },
                  {
                    "id": "7gFV5zYPBw",
                    "position": 8.233,
                    "connectedRight": true,
                    "handles": [
                      0.5,
                      1,
                      0.5,
                      0
                    ],
                    "type": "bezier",
                    "value": 1.8
                  },
                  {
                    "id": "jnjQNrkC6k",
                    "position": 10,
                    "connectedRight": true,
                    "handles": [
                      0.5,
                      1,
                      0.5,
                      0
                    ],
                    "type": "bezier",
                    "value": 1.6
                  }
                ]
              },
              "WY4IruWtyu": {
                "type": "BasicKeyframedTrack",
                "__debugName": "Armor:[\"position\",\"y\"]",
                "keyframes": [
                  {
                    "id": "Y-lgoHwdBW",
                    "position": 0,
                    "connectedRight": true,
                    "handles": [
                      0.5,
                      1,
                      0.5,
                      0
                    ],
                    "type": "bezier",
                    "value": 0
                  },
                  {
                    "id": "AeUGeJt3yy",
                    "position": 1.067,
                    "connectedRight": true,
                    "handles": [
                      0.5,
                      1,
                      0.5,
                      0
                    ],
                    "type": "bezier",
                    "value": -0.11534936469579017
                  },
                  {
                    "id": "KCFuvtsWun",
                    "position": 1.8,
                    "connectedRight": true,
                    "handles": [
                      0.5,
                      1,
                      0.5,
                      0
                    ],
                    "type": "bezier",
                    "value": -1.2300000000000004
                  },
                  {
                    "id": "R8ShN8cMdM",
                    "position": 2.367,
                    "connectedRight": true,
                    "handles": [
                      0.5,
                      1,
                      0.5,
                      0
                    ],
                    "type": "bezier",
                    "value": 0.020000000000004903
                  },
                  {
                    "id": "o1x84srA9U",
                    "position": 2.967,
                    "connectedRight": true,
                    "handles": [
                      0.5,
                      1,
                      0.5,
                      0
                    ],
                    "type": "bezier",
                    "value": 0.8503505654805872
                  },
                  {
                    "id": "mG2-HEn41N",
                    "position": 3.533,
                    "connectedRight": true,
                    "handles": [
                      0.5,
                      1,
                      0.5,
                      0
                    ],
                    "type": "bezier",
                    "value": 1.1399999999999997
                  },
                  {
                    "id": "BAOAm6BK1i",
                    "position": 4.133,
                    "connectedRight": true,
                    "handles": [
                      0.5,
                      1,
                      0.5,
                      0
                    ],
                    "type": "bezier",
                    "value": -2.5
                  },
                  {
                    "id": "Qy0cGDOFcz",
                    "position": 4.733,
                    "connectedRight": true,
                    "handles": [
                      0.5,
                      1,
                      0.5,
                      0
                    ],
                    "type": "bezier",
                    "value": 2.1297251172570655
                  },
                  {
                    "id": "Qa4emknp2K",
                    "position": 5.367,
                    "connectedRight": true,
                    "handles": [
                      0.5,
                      1,
                      0.5,
                      0
                    ],
                    "type": "bezier",
                    "value": -2.8699999999999957
                  },
                  {
                    "id": "1qF-YaqdBW",
                    "position": 5.9,
                    "connectedRight": true,
                    "handles": [
                      0.5,
                      1,
                      0.5,
                      0
                    ],
                    "type": "bezier",
                    "value": -0.8599999999999994
                  },
                  {
                    "id": "rtACHYl4mu",
                    "position": 7.667,
                    "connectedRight": true,
                    "handles": [
                      0.5,
                      1,
                      0.5,
                      0
                    ],
                    "type": "bezier",
                    "value": -1.8900000000000057
                  },
                  {
                    "id": "Bm7iQXASrF",
                    "position": 8.233,
                    "connectedRight": true,
                    "handles": [
                      0.5,
                      1,
                      0.5,
                      0
                    ],
                    "type": "bezier",
                    "value": -1.8900000000000057
                  },
                  {
                    "id": "SmkUMChN6i",
                    "position": 10,
                    "connectedRight": true,
                    "handles": [
                      0.5,
                      1,
                      0.5,
                      0
                    ],
                    "type": "bezier",
                    "value": 0
                  }
                ]
              },
              "Ky0xmpQDj5": {
                "type": "BasicKeyframedTrack",
                "__debugName": "Armor:[\"position\",\"z\"]",
                "keyframes": [
                  {
                    "id": "jwkHibzZ4m",
                    "position": 0,
                    "connectedRight": true,
                    "handles": [
                      0.5,
                      1,
                      0.5,
                      0
                    ],
                    "type": "bezier",
                    "value": 0
                  },
                  {
                    "id": "Pp-BtDV8Qn",
                    "position": 1.067,
                    "connectedRight": true,
                    "handles": [
                      0.5,
                      1,
                      0.5,
                      0
                    ],
                    "type": "bezier",
                    "value": 0
                  },
                  {
                    "id": "3Go2Z5GLqd",
                    "position": 1.8,
                    "connectedRight": true,
                    "handles": [
                      0.5,
                      1,
                      0.5,
                      0
                    ],
                    "type": "bezier",
                    "value": 0
                  },
                  {
                    "id": "B9GcX5JFDU",
                    "position": 2.367,
                    "connectedRight": true,
                    "handles": [
                      0.5,
                      1,
                      0.5,
                      0
                    ],
                    "type": "bezier",
                    "value": 0
                  },
                  {
                    "id": "POYN7Dy3Tz",
                    "position": 2.967,
                    "connectedRight": true,
                    "handles": [
                      0.5,
                      1,
                      0.5,
                      0
                    ],
                    "type": "bezier",
                    "value": 0
                  },
                  {
                    "id": "TUt6NWRycU",
                    "position": 3.533,
                    "connectedRight": true,
                    "handles": [
                      0.5,
                      1,
                      0.5,
                      0
                    ],
                    "type": "bezier",
                    "value": 0
                  },
                  {
                    "id": "r3PR1IMl4O",
                    "position": 4.133,
                    "connectedRight": true,
                    "handles": [
                      0.5,
                      1,
                      0.5,
                      0
                    ],
                    "type": "bezier",
                    "value": 0
                  },
                  {
                    "id": "wkoZcezsT9",
                    "position": 4.733,
                    "connectedRight": true,
                    "handles": [
                      0.5,
                      1,
                      0.5,
                      0
                    ],
                    "type": "bezier",
                    "value": 0
                  },
                  {
                    "id": "oVyX0Gimbj",
                    "position": 5.367,
                    "connectedRight": true,
                    "handles": [
                      0.5,
                      1,
                      0.5,
                      0
                    ],
                    "type": "bezier",
                    "value": 0
                  },
                  {
                    "id": "UHO7TtAX2S",
                    "position": 5.9,
                    "connectedRight": true,
                    "handles": [
                      0.5,
                      1,
                      0.5,
                      0
                    ],
                    "type": "bezier",
                    "value": 0
                  },
                  {
                    "id": "8dVYTDkLpQ",
                    "position": 7.667,
                    "connectedRight": true,
                    "handles": [
                      0.5,
                      1,
                      0.5,
                      0
                    ],
                    "type": "bezier",
                    "value": 0
                  },
                  {
                    "id": "VAPH_z7A1o",
                    "position": 8.233,
                    "connectedRight": true,
                    "handles": [
                      0.5,
                      1,
                      0.5,
                      0
                    ],
                    "type": "bezier",
                    "value": 0
                  },
                  {
                    "id": "degL3ikTr-",
                    "position": 10,
                    "connectedRight": true,
                    "handles": [
                      0.5,
                      1,
                      0.5,
                      0
                    ],
                    "type": "bezier",
                    "value": 0
                  }
                ]
              },
              "pUZ86W-Q63": {
                "type": "BasicKeyframedTrack",
                "__debugName": "Armor:[\"rotation\",\"x\"]",
                "keyframes": [
                  {
                    "id": "nRyAVcyvt3",
                    "position": 0,
                    "connectedRight": true,
                    "handles": [
                      0.5,
                      1,
                      0.5,
                      0
                    ],
                    "type": "bezier",
                    "value": 0
                  },
                  {
                    "id": "7rY8EPdzyN",
                    "position": 1.067,
                    "connectedRight": true,
                    "handles": [
                      0.5,
                      1,
                      0.5,
                      0
                    ],
                    "type": "bezier",
                    "value": 0
                  },
                  {
                    "id": "eNX-l-HVyx",
                    "position": 1.8,
                    "connectedRight": true,
                    "handles": [
                      0.5,
                      1,
                      0.5,
                      0
                    ],
                    "type": "bezier",
                    "value": 0
                  },
                  {
                    "id": "bTZy7SQJX-",
                    "position": 2.367,
                    "connectedRight": true,
                    "handles": [
                      0.5,
                      1,
                      0.5,
                      0
                    ],
                    "type": "bezier",
                    "value": 0
                  },
                  {
                    "id": "Yxn24_6DZ9",
                    "position": 2.967,
                    "connectedRight": true,
                    "handles": [
                      0.5,
                      1,
                      0.5,
                      0
                    ],
                    "type": "bezier",
                    "value": 0
                  },
                  {
                    "id": "fh2S0o0xTb",
                    "position": 3.533,
                    "connectedRight": true,
                    "handles": [
                      0.5,
                      1,
                      0.5,
                      0
                    ],
                    "type": "bezier",
                    "value": 0
                  },
                  {
                    "id": "XyJK-hSvok",
                    "position": 4.133,
                    "connectedRight": true,
                    "handles": [
                      0.5,
                      1,
                      0.5,
                      0
                    ],
                    "type": "bezier",
                    "value": 0.35000000000000003
                  },
                  {
                    "id": "hFELBATkiJ",
                    "position": 4.733,
                    "connectedRight": true,
                    "handles": [
                      0.5,
                      1,
                      0.5,
                      0
                    ],
                    "type": "bezier",
                    "value": -0.25
                  },
                  {
                    "id": "APUkwxJOxd",
                    "position": 5.367,
                    "connectedRight": true,
                    "handles": [
                      0.5,
                      1,
                      0.5,
                      0
                    ],
                    "type": "bezier",
                    "value": 0
                  },
                  {
                    "id": "98PY0F-x3z",
                    "position": 5.9,
                    "connectedRight": true,
                    "handles": [
                      0.5,
                      1,
                      0.5,
                      0
                    ],
                    "type": "bezier",
                    "value": 0
                  },
                  {
                    "id": "ELxiiXwacz",
                    "position": 7.667,
                    "connectedRight": true,
                    "handles": [
                      0.5,
                      1,
                      0.5,
                      0
                    ],
                    "type": "bezier",
                    "value": 0
                  },
                  {
                    "id": "gI_-u6fBFZ",
                    "position": 8.233,
                    "connectedRight": true,
                    "handles": [
                      0.5,
                      1,
                      0.5,
                      0
                    ],
                    "type": "bezier",
                    "value": 0
                  },
                  {
                    "id": "0zNbdWLVw3",
                    "position": 10,
                    "connectedRight": true,
                    "handles": [
                      0.5,
                      1,
                      0.5,
                      0
                    ],
                    "type": "bezier",
                    "value": 0
                  }
                ]
              },
              "gXt05OH_eR": {
                "type": "BasicKeyframedTrack",
                "__debugName": "Armor:[\"rotation\",\"y\"]",
                "keyframes": [
                  {
                    "id": "rTeM6DvKGu",
                    "position": 0,
                    "connectedRight": true,
                    "handles": [
                      0.5,
                      1,
                      0.5,
                      0
                    ],
                    "type": "bezier",
                    "value": -0.3900000000000002
                  },
                  {
                    "id": "JTYrd_WsIR",
                    "position": 1.067,
                    "connectedRight": true,
                    "handles": [
                      0.5,
                      1,
                      0.5,
                      0
                    ],
                    "type": "bezier",
                    "value": -0.46139745878316113
                  },
                  {
                    "id": "MKI3wZndz4",
                    "position": 1.8,
                    "connectedRight": true,
                    "handles": [
                      0.5,
                      1,
                      0.5,
                      0
                    ],
                    "type": "bezier",
                    "value": -0.6800000000000004
                  },
                  {
                    "id": "7r9qz96RpT",
                    "position": 2.367,
                    "connectedRight": true,
                    "handles": [
                      0.5,
                      1,
                      0.5,
                      0
                    ],
                    "type": "bezier",
                    "value": 1.0999999999999999
                  },
                  {
                    "id": "LqQXutQJYz",
                    "position": 2.967,
                    "connectedRight": true,
                    "handles": [
                      0.5,
                      1,
                      0.5,
                      0
                    ],
                    "type": "bezier",
                    "value": -0.1299999999999999
                  },
                  {
                    "id": "TZZXjvQ_qD",
                    "position": 3.533,
                    "connectedRight": true,
                    "handles": [
                      0.5,
                      1,
                      0.5,
                      0
                    ],
                    "type": "bezier",
                    "value": -0.6500000000000001
                  },
                  {
                    "id": "m_uM6C1YQ0",
                    "position": 4.133,
                    "connectedRight": true,
                    "handles": [
                      0.5,
                      1,
                      0.5,
                      0
                    ],
                    "type": "bezier",
                    "value": 0.10999999999999978
                  },
                  {
                    "id": "tfYLXdObkc",
                    "position": 4.733,
                    "connectedRight": true,
                    "handles": [
                      0.5,
                      1,
                      0.5,
                      0
                    ],
                    "type": "bezier",
                    "value": -1.0900000000000003
                  },
                  {
                    "id": "hxLYp1E0z5",
                    "position": 5.367,
                    "connectedRight": true,
                    "handles": [
                      0.5,
                      1,
                      0.5,
                      0
                    ],
                    "type": "bezier",
                    "value": -0.1499999999999999
                  },
                  {
                    "id": "wMWm6uJP3k",
                    "position": 5.9,
                    "connectedRight": true,
                    "handles": [
                      0.5,
                      1,
                      0.5,
                      0
                    ],
                    "type": "bezier",
                    "value": -0.22000000000000008
                  },
                  {
                    "id": "YeXgxJdVeB",
                    "position": 7.667,
                    "connectedRight": true,
                    "handles": [
                      0.5,
                      1,
                      0.5,
                      0
                    ],
                    "type": "bezier",
                    "value": -3.379999999999995
                  },
                  {
                    "id": "Oo_W2QFtUj",
                    "position": 8.233,
                    "connectedRight": true,
                    "handles": [
                      0.5,
                      1,
                      0.5,
                      0
                    ],
                    "type": "bezier",
                    "value": -3.379999999999995
                  },
                  {
                    "id": "GcYq8D_VMm",
                    "position": 10,
                    "connectedRight": true,
                    "handles": [
                      0.5,
                      1,
                      0.5,
                      0
                    ],
                    "type": "bezier",
                    "value": -0.5000000000000001
                  }
                ]
              },
              "eNdsdo0-k_": {
                "type": "BasicKeyframedTrack",
                "__debugName": "Armor:[\"rotation\",\"z\"]",
                "keyframes": [
                  {
                    "id": "v5iIt-EeHV",
                    "position": 0,
                    "connectedRight": true,
                    "handles": [
                      0.5,
                      1,
                      0.5,
                      0
                    ],
                    "type": "bezier",
                    "value": 0
                  },
                  {
                    "id": "oTI--vo0AG",
                    "position": 1.067,
                    "connectedRight": true,
                    "handles": [
                      0.5,
                      1,
                      0.5,
                      0
                    ],
                    "type": "bezier",
                    "value": 0
                  },
                  {
                    "id": "6a9_Vi5g-X",
                    "position": 1.8,
                    "connectedRight": true,
                    "handles": [
                      0.5,
                      1,
                      0.5,
                      0
                    ],
                    "type": "bezier",
                    "value": 0
                  },
                  {
                    "id": "lZLVQP-0El",
                    "position": 2.367,
                    "connectedRight": true,
                    "handles": [
                      0.5,
                      1,
                      0.5,
                      0
                    ],
                    "type": "bezier",
                    "value": 0
                  },
                  {
                    "id": "P0fi4wsyZ3",
                    "position": 2.967,
                    "connectedRight": true,
                    "handles": [
                      0.5,
                      1,
                      0.5,
                      0
                    ],
                    "type": "bezier",
                    "value": 0
                  },
                  {
                    "id": "XW3AauMroH",
                    "position": 3.533,
                    "connectedRight": true,
                    "handles": [
                      0.5,
                      1,
                      0.5,
                      0
                    ],
                    "type": "bezier",
                    "value": 0
                  },
                  {
                    "id": "VbzDJglHKV",
                    "position": 4.133,
                    "connectedRight": true,
                    "handles": [
                      0.5,
                      1,
                      0.5,
                      0
                    ],
                    "type": "bezier",
                    "value": 0
                  },
                  {
                    "id": "boAR8NbzLr",
                    "position": 4.733,
                    "connectedRight": true,
                    "handles": [
                      0.5,
                      1,
                      0.5,
                      0
                    ],
                    "type": "bezier",
                    "value": 0
                  },
                  {
                    "id": "_c8McS22k7",
                    "position": 5.367,
                    "connectedRight": true,
                    "handles": [
                      0.5,
                      1,
                      0.5,
                      0
                    ],
                    "type": "bezier",
                    "value": 0
                  },
                  {
                    "id": "Jc5ZZa87KZ",
                    "position": 5.9,
                    "connectedRight": true,
                    "handles": [
                      0.5,
                      1,
                      0.5,
                      0
                    ],
                    "type": "bezier",
                    "value": 0
                  },
                  {
                    "id": "ay-E9olqHh",
                    "position": 7.667,
                    "connectedRight": true,
                    "handles": [
                      0.5,
                      1,
                      0.5,
                      0
                    ],
                    "type": "bezier",
                    "value": 0
                  },
                  {
                    "id": "dir0She0vo",
                    "position": 8.233,
                    "connectedRight": true,
                    "handles": [
                      0.5,
                      1,
                      0.5,
                      0
                    ],
                    "type": "bezier",
                    "value": 0
                  },
                  {
                    "id": "TCetzo7LQo",
                    "position": 10,
                    "connectedRight": true,
                    "handles": [
                      0.5,
                      1,
                      0.5,
                      0
                    ],
                    "type": "bezier",
                    "value": 0
                  }
                ]
              },
              "joPMjkvqUt": {
                "type": "BasicKeyframedTrack",
                "__debugName": "Armor:[\"scale\",\"x\"]",
                "keyframes": [
                  {
                    "id": "x42o0x7zra",
                    "position": 0,
                    "connectedRight": true,
                    "handles": [
                      0.5,
                      1,
                      0.5,
                      0
                    ],
                    "type": "bezier",
                    "value": 1
                  },
                  {
                    "id": "tRFbkZYsP-",
                    "position": 1.067,
                    "connectedRight": true,
                    "handles": [
                      0.5,
                      1,
                      0.5,
                      0
                    ],
                    "type": "bezier",
                    "value": 1.2
                  },
                  {
                    "id": "_tmcpi36Lj",
                    "position": 1.8,
                    "connectedRight": true,
                    "handles": [
                      0.5,
                      1,
                      0.5,
                      0
                    ],
                    "type": "bezier",
                    "value": 1.6
                  },
                  {
                    "id": "MvlKCgWl2d",
                    "position": 2.367,
                    "connectedRight": true,
                    "handles": [
                      0.5,
                      1,
                      0.5,
                      0
                    ],
                    "type": "bezier",
                    "value": 2
                  },
                  {
                    "id": "Qj870-ZWYE",
                    "position": 2.967,
                    "connectedRight": true,
                    "handles": [
                      0.5,
                      1,
                      0.5,
                      0
                    ],
                    "type": "bezier",
                    "value": 2
                  },
                  {
                    "id": "8AtbWa3gqr",
                    "position": 3.533,
                    "connectedRight": true,
                    "handles": [
                      0.5,
                      1,
                      0.5,
                      0
                    ],
                    "type": "bezier",
                    "value": 2.2
                  },
                  {
                    "id": "xRKUZLjDCW",
                    "position": 4.133,
                    "connectedRight": true,
                    "handles": [
                      0.5,
                      1,
                      0.5,
                      0
                    ],
                    "type": "bezier",
                    "value": 2.2
                  },
                  {
                    "id": "ZHSGdHNnxS",
                    "position": 4.733,
                    "connectedRight": true,
                    "handles": [
                      0.5,
                      1,
                      0.5,
                      0
                    ],
                    "type": "bezier",
                    "value": 2.2
                  },
                  {
                    "id": "aIvGdW0qW2",
                    "position": 5.367,
                    "connectedRight": true,
                    "handles": [
                      0.5,
                      1,
                      0.5,
                      0
                    ],
                    "type": "bezier",
                    "value": 2.2
                  },
                  {
                    "id": "3MX4r0YQrU",
                    "position": 5.9,
                    "connectedRight": true,
                    "handles": [
                      0.5,
                      1,
                      0.5,
                      0
                    ],
                    "type": "bezier",
                    "value": 1.5
                  },
                  {
                    "id": "lABsWBWBEp",
                    "position": 7.667,
                    "connectedRight": true,
                    "handles": [
                      0.5,
                      1,
                      0.5,
                      0
                    ],
                    "type": "bezier",
                    "value": 1.8
                  },
                  {
                    "id": "UxUJXMQrzN",
                    "position": 8.233,
                    "connectedRight": true,
                    "handles": [
                      0.5,
                      1,
                      0.5,
                      0
                    ],
                    "type": "bezier",
                    "value": 2.5
                  },
                  {
                    "id": "ymxNDWl5HH",
                    "position": 10,
                    "connectedRight": true,
                    "handles": [
                      0.5,
                      1,
                      0.5,
                      0
                    ],
                    "type": "bezier",
                    "value": 1
                  }
                ]
              },
              "ADlU6CAbt4": {
                "type": "BasicKeyframedTrack",
                "__debugName": "Armor:[\"scale\",\"y\"]",
                "keyframes": [
                  {
                    "id": "P15UOe__Kl",
                    "position": 0,
                    "connectedRight": true,
                    "handles": [
                      0.5,
                      1,
                      0.5,
                      0
                    ],
                    "type": "bezier",
                    "value": 1
                  },
                  {
                    "id": "rA39M8ddO6",
                    "position": 1.067,
                    "connectedRight": true,
                    "handles": [
                      0.5,
                      1,
                      0.5,
                      0
                    ],
                    "type": "bezier",
                    "value": 1.2
                  },
                  {
                    "id": "JogmhcoOgw",
                    "position": 1.8,
                    "connectedRight": true,
                    "handles": [
                      0.5,
                      1,
                      0.5,
                      0
                    ],
                    "type": "bezier",
                    "value": 1.6
                  },
                  {
                    "id": "Mg-DkNNE9I",
                    "position": 2.367,
                    "connectedRight": true,
                    "handles": [
                      0.5,
                      1,
                      0.5,
                      0
                    ],
                    "type": "bezier",
                    "value": 2
                  },
                  {
                    "id": "gev9m4QFSK",
                    "position": 2.967,
                    "connectedRight": true,
                    "handles": [
                      0.5,
                      1,
                      0.5,
                      0
                    ],
                    "type": "bezier",
                    "value": 2
                  },
                  {
                    "id": "xUIg_y__k9",
                    "position": 3.533,
                    "connectedRight": true,
                    "handles": [
                      0.5,
                      1,
                      0.5,
                      0
                    ],
                    "type": "bezier",
                    "value": 2.2
                  },
                  {
                    "id": "KMaV8VuB4J",
                    "position": 4.133,
                    "connectedRight": true,
                    "handles": [
                      0.5,
                      1,
                      0.5,
                      0
                    ],
                    "type": "bezier",
                    "value": 2.2
                  },
                  {
                    "id": "ruWfL5aH3O",
                    "position": 4.733,
                    "connectedRight": true,
                    "handles": [
                      0.5,
                      1,
                      0.5,
                      0
                    ],
                    "type": "bezier",
                    "value": 2.2
                  },
                  {
                    "id": "Ja655ZE-ck",
                    "position": 5.367,
                    "connectedRight": true,
                    "handles": [
                      0.5,
                      1,
                      0.5,
                      0
                    ],
                    "type": "bezier",
                    "value": 2.2
                  },
                  {
                    "id": "ftjGyfdjGN",
                    "position": 5.9,
                    "connectedRight": true,
                    "handles": [
                      0.5,
                      1,
                      0.5,
                      0
                    ],
                    "type": "bezier",
                    "value": 1.5
                  },
                  {
                    "id": "zPsXsFDn2y",
                    "position": 7.667,
                    "connectedRight": true,
                    "handles": [
                      0.5,
                      1,
                      0.5,
                      0
                    ],
                    "type": "bezier",
                    "value": 1.8
                  },
                  {
                    "id": "6LhFIcDf1g",
                    "position": 8.233,
                    "connectedRight": true,
                    "handles": [
                      0.5,
                      1,
                      0.5,
                      0
                    ],
                    "type": "bezier",
                    "value": 2.5
                  },
                  {
                    "id": "ObDptkxPCm",
                    "position": 10,
                    "connectedRight": true,
                    "handles": [
                      0.5,
                      1,
                      0.5,
                      0
                    ],
                    "type": "bezier",
                    "value": 1
                  }
                ]
              },
              "a5joimTFSp": {
                "type": "BasicKeyframedTrack",
                "__debugName": "Armor:[\"scale\",\"z\"]",
                "keyframes": [
                  {
                    "id": "DOf5L0YJaP",
                    "position": 0,
                    "connectedRight": true,
                    "handles": [
                      0.5,
                      1,
                      0.5,
                      0
                    ],
                    "type": "bezier",
                    "value": 1
                  },
                  {
                    "id": "VFxEtKPEMr",
                    "position": 1.067,
                    "connectedRight": true,
                    "handles": [
                      0.5,
                      1,
                      0.5,
                      0
                    ],
                    "type": "bezier",
                    "value": 1.2
                  },
                  {
                    "id": "auX4AaOsuC",
                    "position": 1.8,
                    "connectedRight": true,
                    "handles": [
                      0.5,
                      1,
                      0.5,
                      0
                    ],
                    "type": "bezier",
                    "value": 1.6
                  },
                  {
                    "id": "yadG2Q55bo",
                    "position": 2.367,
                    "connectedRight": true,
                    "handles": [
                      0.5,
                      1,
                      0.5,
                      0
                    ],
                    "type": "bezier",
                    "value": 2
                  },
                  {
                    "id": "aKhgUlx0mE",
                    "position": 2.967,
                    "connectedRight": true,
                    "handles": [
                      0.5,
                      1,
                      0.5,
                      0
                    ],
                    "type": "bezier",
                    "value": 2
                  },
                  {
                    "id": "-dd--VQ2gf",
                    "position": 3.533,
                    "connectedRight": true,
                    "handles": [
                      0.5,
                      1,
                      0.5,
                      0
                    ],
                    "type": "bezier",
                    "value": 2
                  },
                  {
                    "id": "ELcI6RkHca",
                    "position": 4.133,
                    "connectedRight": true,
                    "handles": [
                      0.5,
                      1,
                      0.5,
                      0
                    ],
                    "type": "bezier",
                    "value": 2.2
                  },
                  {
                    "id": "iyeMWR4yTn",
                    "position": 4.733,
                    "connectedRight": true,
                    "handles": [
                      0.5,
                      1,
                      0.5,
                      0
                    ],
                    "type": "bezier",
                    "value": 2.2
                  },
                  {
                    "id": "GkckHZog0f",
                    "position": 5.367,
                    "connectedRight": true,
                    "handles": [
                      0.5,
                      1,
                      0.5,
                      0
                    ],
                    "type": "bezier",
                    "value": 2.2
                  },
                  {
                    "id": "eF7kb0O-I-",
                    "position": 5.9,
                    "connectedRight": true,
                    "handles": [
                      0.5,
                      1,
                      0.5,
                      0
                    ],
                    "type": "bezier",
                    "value": 1.5
                  },
                  {
                    "id": "JqmkcXnPLJ",
                    "position": 7.667,
                    "connectedRight": true,
                    "handles": [
                      0.5,
                      1,
                      0.5,
                      0
                    ],
                    "type": "bezier",
                    "value": 1.8
                  },
                  {
                    "id": "eIAq1C9Tcc",
                    "position": 8.233,
                    "connectedRight": true,
                    "handles": [
                      0.5,
                      1,
                      0.5,
                      0
                    ],
                    "type": "bezier",
                    "value": 2.5
                  },
                  {
                    "id": "4UhY2_lMrH",
                    "position": 10,
                    "connectedRight": true,
                    "handles": [
                      0.5,
                      1,
                      0.5,
                      0
                    ],
                    "type": "bezier",
                    "value": 1
                  }
                ]
              }
            },
            "trackIdByPropPath": {
              "[\"position\",\"x\"]": "JVi37YVWqn",
              "[\"position\",\"y\"]": "WY4IruWtyu",
              "[\"position\",\"z\"]": "Ky0xmpQDj5",
              "[\"rotation\",\"x\"]": "pUZ86W-Q63",
              "[\"rotation\",\"y\"]": "gXt05OH_eR",
              "[\"rotation\",\"z\"]": "eNdsdo0-k_",
              "[\"scale\",\"x\"]": "joPMjkvqUt",
              "[\"scale\",\"y\"]": "ADlU6CAbt4",
              "[\"scale\",\"z\"]": "a5joimTFSp"
            }
          }
        }
      }
    }
  },
  "definitionVersion": "0.4.0",
  "revisionHistory": [
    "q7EAz5WjRS6G4GVb",
    "vIct-nHfKIM5iIla"
  ]
}